{"compressionlevel":-1,"height":20,"infinite":true,"layers":[{"draworder":"topdown","id":3,"name":"Floor","objects":[],"opacity":1,"type":"objectgroup","visible":true,"x":0,"y":0},{"draworder":"topdown","id":4,"name":"Shadow","objects":[{"gid":570,"height":416,"id":100,"name":"","properties":[{"name":"tint","type":"color","value":"#c8000000"}],"rotation":0,"type":"","visible":true,"width":368,"x":352,"y":-620},{"gid":570,"height":416,"id":101,"name":"","properties":[{"name":"tint","type":"color","value":"#c8000000"}],"rotation":0,"type":"","visible":true,"width":368,"x":404,"y":-392},{"gid":570,"height":416,"id":113,"name":"","properties":[{"name":"tint","type":"color","value":"#c8000000"}],"rotation":0,"type":"","visible":true,"width":368,"x":-736,"y":-516},{"gid":570,"height":416,"id":114,"name":"","properties":[{"name":"tint","type":"color","value":"#c8000000"}],"rotation":0,"type":"","visible":true,"width":368,"x":-776,"y":-296},{"gid":570,"height":416,"id":115,"name":"","properties":[{"name":"tint","type":"color","value":"#c8000000"}],"rotation":0,"type":"","visible":true,"width":368,"x":-992,"y":-280},{"gid":570,"height":416,"id":116,"name":"","properties":[{"name":"tint","type":"color","value":"#c8000000"}],"rotation":0,"type":"","visible":true,"width":368,"x":-1188,"y":-288},{"gid":570,"height":416,"id":117,"name":"","properties":[{"name":"tint","type":"color","value":"#c8000000"}],"rotation":0,"type":"","visible":true,"width":368,"x":-788,"y":182},{"gid":570,"height":416,"id":118,"name":"","properties":[{"name":"tint","type":"color","value":"#c8000000"}],"rotation":0,"type":"","visible":true,"width":368,"x":-892,"y":290},{"gid":570,"height":416,"id":119,"name":"","properties":[{"name":"tint","type":"color","value":"#c8000000"}],"rotation":0,"type":"","visible":true,"width":368,"x":-976,"y":382},{"gid":570,"height":416,"id":120,"name":"","properties":[{"name":"tint","type":"color","value":"#c8000000"}],"rotation":0,"type":"","visible":true,"width":368,"x":-1140,"y":362},{"gid":570,"height":416,"id":102,"name":"","properties":[{"name":"tint","type":"color","value":"#c8000000"}],"rotation":0,"type":"","visible":true,"width":368,"x":464,"y":-152},{"gid":570,"height":416,"id":103,"name":"","properties":[{"name":"tint","type":"color","value":"#c8000000"}],"rotation":0,"type":"","visible":true,"width":368,"x":560,"y":84},{"gid":570,"height":306,"id":104,"name":"","properties":[{"name":"tint","type":"color","value":"#c8000000"}],"rotation":0,"type":"","visible":true,"width":368,"x":488,"y":232},{"gid":570,"height":416,"id":105,"name":"","properties":[{"name":"tint","type":"color","value":"#c8000000"}],"rotation":0,"type":"","visible":true,"width":368,"x":636,"y":382},{"gid":570,"height":416,"id":106,"name":"","properties":[{"name":"tint","type":"color","value":"#c8000000"}],"rotation":0,"type":"","visible":true,"width":368,"x":328,"y":-860},{"gid":570,"height":416,"id":107,"name":"","properties":[{"name":"tint","type":"color","value":"#c8000000"}],"rotation":0,"type":"","visible":true,"width":368,"x":760,"y":-648},{"gid":570,"height":416,"id":108,"name":"","properties":[{"name":"tint","type":"color","value":"#c8000000"}],"rotation":0,"type":"","visible":true,"width":368,"x":904,"y":-680}],"opacity":1,"type":"objectgroup","visible":true,"x":0,"y":0},{"draworder":"topdown","id":2,"name":"Gameplay","objects":[{"gid":563,"height":491,"id":90,"name":"","rotation":0,"type":"","visible":true,"width":384,"x":564,"y":-96},{"gid":563,"height":491,"id":93,"name":"","rotation":0,"type":"","visible":true,"width":384,"x":512,"y":-352},{"gid":562,"height":333,"id":94,"name":"","rotation":1.16282,"type":"","visible":true,"width":604,"x":475.371,"y":-773.852},{"gid":2147484210,"height":333,"id":109,"name":"","rotation":358.652,"type":"","visible":true,"width":604,"x":-1117.31,"y":-368.69},{"gid":2147484210,"height":333,"id":111,"name":"","rotation":358.652,"type":"","visible":true,"width":604,"x":-1098.68,"y":-597.191},{"gid":2147484215,"height":366,"id":95,"name":"","rotation":357.258566368649,"type":"","visible":true,"width":88,"x":-558.165460551747,"y":-761.655554304559},{"gid":567,"height":366,"id":123,"name":"","rotation":1.16282,"type":"","visible":true,"width":88,"x":449.326,"y":-862.481},{"gid":564,"height":582,"id":97,"name":"","rotation":0,"type":"","visible":true,"width":507,"x":554,"y":308},{"gid":2147484212,"height":582,"id":112,"name":"","rotation":0,"type":"","visible":true,"width":507,"x":-1054,"y":264},{"gid":566,"height":734,"id":121,"name":"","rotation":0,"type":"","visible":true,"width":499,"x":443,"y":-969},{"gid":568,"height":124,"id":122,"name":"","rotation":0,"type":"","visible":true,"width":69,"x":404,"y":-856},{"gid":565,"height":91.3043,"id":124,"name":"","rotation":0,"type":"","visible":true,"width":56,"x":-614,"y":-339.696},{"gid":566,"height":734,"id":125,"name":"","rotation":0,"type":"","visible":true,"width":499,"x":-899,"y":-819},{"gid":566,"height":734,"id":126,"name":"","rotation":0,"type":"","visible":true,"width":499,"x":-1175,"y":-861},{"gid":566,"height":734,"id":127,"name":"","rotation":0,"type":"","visible":true,"width":499,"x":-945,"y":-1029},{"gid":566,"height":734,"id":128,"name":"","rotation":0,"type":"","visible":true,"width":499,"x":-1157,"y":-205},{"gid":566,"height":734,"id":129,"name":"","rotation":0,"type":"","visible":true,"width":499,"x":687,"y":-595},{"height":566,"id":130,"name":"","rotation":0,"type":"DeadZone","visible":true,"width":830,"x":-378,"y":-2406},{"gid":2147484210,"height":350.732359341001,"id":131,"name":"","rotation":0,"type":"","visible":true,"width":630.000466272925,"x":-1024.8786866175,"y":-1144},{"gid":562,"height":350.732359341001,"id":132,"name":"","rotation":0,"type":"","visible":true,"width":630.000466272925,"x":398.908523374874,"y":-1108.54036793173}],"opacity":1,"type":"objectgroup","visible":true,"x":0,"y":0},{"draworder":"topdown","id":5,"name":"Settings","objects":[],"opacity":1,"type":"objectgroup","visible":true,"x":0,"y":0}],"nextlayerid":6,"nextobjectid":133,"orientation":"orthogonal","renderorder":"right-down","tiledversion":"1.10.2","tileheight":32,"tilesets":[{"firstgid":1,"source":"../../../../tiled/survival/tileset/forest1.tsx"},{"firstgid":317,"source":"../../../../tiled/tileset/urban1.tsx"},{"firstgid":561,"source":"../../../../tiled/survival/tileset/survive-props.tsx"},{"firstgid":571,"source":"../../../../tiled/survival/tileset/forestTextures.tsx"}],"tilewidth":32,"type":"map","version":"1.10","width":30}