{"ORC_WARRIOR_01":{"name":"Orc Warrior","attack":8,"defense":7,"dexterity":5,"magic":2,"magic_defense":3,"range":1,"special_ability_id":"ORC_WARRIOR_RAMPAGE"},"ELF_MAGE_01":{"name":"Elf Mage","magic":9,"magic_defense":7,"dexterity":6,"range":8,"special_ability_id":"ELF_MAGE_NATURES_WRATH"},"CAVALIER_01":{"name":"Cavalier","attack":7,"defense":8,"dexterity":6,"magic":2,"magic_defense":2,"range":1,"special_ability_id":"CAVALIER_CHARGE"},"DWARF_DEFENDER_01":{"name":"Dwarf Defender","attack":6,"defense":9,"dexterity":4,"magic":1,"magic_defense":4,"range":1,"special_ability_id":"DWARF_DEFENDER_STONE_SHIELD"},"ORC_SHAMAN_01":{"name":"Orc Shaman","magic":8,"magic_defense":6,"dexterity":5,"range":7,"special_ability_id":"ORC_SHAMAN_FURY_OF_ELEMENTS"},"ELF_ARCHER_01":{"name":"Elf Archer","attack":7,"defense":6,"dexterity":9,"magic":3,"magic_defense":3,"range":9,"special_ability_id":"ELF_ARCHER_PRECISION_SHOT"},"DRAGON_RIDER_01":{"name":"Dragon Rider","attack":9,"defense":8,"dexterity":7,"magic":4,"magic_defense":5,"range":6,"special_ability_id":"DRAGON_RIDER_DRAGONS_BREATH"},"DWARVEN_ENGINEER_01":{"name":"Dwarven Engineer","attack":6,"defense":7,"dexterity":8,"magic":5,"magic_defense":5,"range":8,"special_ability_id":"DWARVEN_ENGINEER_INVENTIVE_CONTRAPTION"},"GOBLIN_ROGUE_01":{"name":"Goblin Rogue","attack":7,"defense":5,"dexterity":9,"magic":2,"magic_defense":2,"range":7,"special_ability_id":"GOBLIN_ROGUE_SHADOW_STRIKE"}}