{"frames":{"tree1":{"frame":{"x":1,"y":1,"w":104.5,"h":139},"rotated":false,"trimmed":true,"spriteSourceSize":{"x":0,"y":0,"w":104.5,"h":139},"sourceSize":{"w":119.5,"h":139},"pivot":{"x":0.5,"y":0.5}},"tree-log":{"frame":{"x":107.5,"y":1,"w":42.5,"h":40},"rotated":true,"trimmed":false,"spriteSourceSize":{"x":0,"y":0,"w":42.5,"h":40},"sourceSize":{"w":42.5,"h":40},"pivot":{"x":0.5,"y":0.5}},"berry":{"frame":{"x":107.5,"y":45.5,"w":23.5,"h":26},"rotated":true,"trimmed":false,"spriteSourceSize":{"x":0,"y":0,"w":23.5,"h":26},"sourceSize":{"w":23.5,"h":26},"pivot":{"x":0.5,"y":0.5}}},"meta":{"app":"http://github.com/odrick/free-tex-packer-core","version":"0.3.4","image":"environment@0.5x.png","format":"RGBA8888","size":{"w":149,"h":141},"scale":0.5}}